scramble_generator/__init__.py
scramble_generator/app.py
scramble_generator/scramble_generator.py
scramble_generator/yaml_file_handler.py
scramble_generator/resources/PYPI_README.md
scramble_generator/resources/configs/config.yaml
scramble_generator/resources/configs/themes.yaml
scramble_generator/resources/gifs/app_install_uninstall_showcase.gif
scramble_generator/resources/gifs/app_showcase.gif
scramble_generator/resources/images/scramble_generator-128.png
scramble_generator/resources/images/scramble_generator-16.png
scramble_generator/resources/images/scramble_generator-256.png
scramble_generator/resources/images/scramble_generator-32.png
scramble_generator/resources/images/scramble_generator-512.png
scramble_generator/resources/images/scramble_generator-64.png
scramble_generator/resources/images/scramble_generator_with_text-128.png
scramble_generator/resources/images/scramble_generator_with_text-16.png
scramble_generator/resources/images/scramble_generator_with_text-256.png
scramble_generator/resources/images/scramble_generator_with_text-32.png
scramble_generator/resources/images/scramble_generator_with_text-512.png
scramble_generator/resources/images/scramble_generator_with_text-64.png
scramble_generator-1.20.3.dist-info/METADATA
scramble_generator-1.20.3.dist-info/WHEEL
scramble_generator-1.20.3.dist-info/entry_points.txt
scramble_generator-1.20.3.dist-info/licenses/LICENSE
scramble_generator-1.20.3.dist-info/RECORD
