Metadata-Version: 2.4
Name: scramble_generator
Version: 1.20.3
Summary: Python app for generating scrambles for twisty puzzles.
Project-URL: repository, https://codeberg.org/melvinquick/scramble_generator
Project-URL: issues, https://codeberg.org/melvinquick/scramble_generator/issues
Author-email: Melvin Quick <melvinquick@proton.me>
License-Expression: MIT
License-File: LICENSE
Requires-Python: >=3.12
Requires-Dist: pyside6>=6.8.2.1
Requires-Dist: pyyaml>=6.0.2
